README.md
setup.py
py_glo_board.egg-info/PKG-INFO
py_glo_board.egg-info/SOURCES.txt
py_glo_board.egg-info/dependency_links.txt
py_glo_board.egg-info/requires.txt
py_glo_board.egg-info/top_level.txt
py_glo_boards_api/__init__.py
py_glo_boards_api/api.py
py_glo_boards_api/types.py