Metadata-Version: 2.1
Name: py-glo-board
Version: 1.0.1
Summary: Python client for GitKraken Glo Boards API
Home-page: https://github.com/dpeite/py-glo-board
Author: Daniel Vilar Peiteado
Author-email: danielvilar2@gmail.com
Maintainer: Daniel Vilar Peiteado
Maintainer-email: danielvilar2@gmail.com
License: UNKNOWN
Project-URL: Bug Reports, https://github.com/dpeite/py-glo-board/issues
Project-URL: Source, https://github.com/dpeite/py-glo-board
Keywords: gitkraken,glo boards
Platform: UNKNOWN
Classifier: Programming Language :: Python :: 3
Classifier: License :: OSI Approved :: MIT License
Classifier: Operating System :: OS Independent
Classifier: Development Status :: 5 - Production/Stable
Classifier: Intended Audience :: Developers
Classifier: Topic :: Software Development :: Libraries :: Python Modules
